fastapi_cloud_healthcheck_aws_s3bucket/__init__.py
fastapi_cloud_healthcheck_aws_s3bucket/bucket_check.py
fastapi_cloud_healthcheck_aws_s3bucket-0.1.1.dist-info/LICENSE
fastapi_cloud_healthcheck_aws_s3bucket-0.1.1.dist-info/METADATA
fastapi_cloud_healthcheck_aws_s3bucket-0.1.1.dist-info/WHEEL
fastapi_cloud_healthcheck_aws_s3bucket-0.1.1.dist-info/RECORD
