Metadata-Version: 2.1
Name: fastapi-cloud-healthcheck-aws-s3bucket
Version: 0.1.1
Summary: This package is designed to validate the operational status of Amazon S3 buckets within an AWS account. It provides comprehensive diagnostics on the accessibility and functionality of an S3 bucket by performing key operations, including Bucket Accessibility, Object Operations and Bucket Policy Validation.
Home-page: https://github.com/yogeshselvarajan/fastapi_cloud_healthcheck_aws_s3bucket
License: MIT
Keywords: fastapi,healthcheck,cloud,boto3,aws,s3,storage
Author: Yogesh Selvarajan
Author-email: yogeshselvarajan@gmail.com
Requires-Python: >=3.8,<4.0
Classifier: Framework :: FastAPI
Classifier: License :: OSI Approved :: MIT License
Classifier: Programming Language :: Python :: 3
Classifier: Programming Language :: Python :: 3.8
Classifier: Programming Language :: Python :: 3.9
Classifier: Programming Language :: Python :: 3.10
Classifier: Programming Language :: Python :: 3.11
Classifier: Programming Language :: Python :: 3.12
Requires-Dist: boto3 (>=1.35.27,<2.0.0)
Requires-Dist: botocore (>=1.35.27,<2.0.0)
Requires-Dist: fastapi_cloud_healthcheck (>=0.1.4,<0.2.0)
Requires-Dist: pytz (>=2024.2,<2025.0)
Project-URL: Repository, https://github.com/yogeshselvarajan/fastapi_cloud_healthcheck_aws_s3bucket
